{"stats":{"minecraft:killed":{"minecraft:squid":1,"fins:swamp_mucker":3,"mysticalworld:clam":2,"goblintraders:goblin_trader":1},"minecraft:broken":{"roughtweaks:salve":1},"minecraft:custom":{"minecraft:interact_with_furnace":16,"minecraft:mob_kills":7,"minecraft:interact_with_crafting_table":9,"minecraft:play_one_minute":46940,"minecraft:leave_game":4,"minecraft:time_since_death":46940,"minecraft:climb_one_cm":289,"minecraft:time_since_rest":46940,"minecraft:sprint_one_cm":55266,"minecraft:damage_taken":14,"minecraft:walk_one_cm":103577,"minecraft:drop":20,"minecraft:damage_dealt":907,"minecraft:swim_one_cm":2602,"minecraft:fly_one_cm":17310,"minecraft:open_chest":11,"minecraft:crouch_one_cm":2479,"minecraft:sneak_time":823,"minecraft:walk_under_water_one_cm":16274,"minecraft:jump":420,"minecraft:walk_on_water_one_cm":14094,"minecraft:fall_one_cm":5675},"minecraft:mined":{"projectvibrantjourneys:cattail":1,"betterdefaultbiomes:gray_mushroom":3,"betterdefaultbiomes:tall_water_reeds":1,"supplementaries:book_pile_horizontal":1,"ars_nouveau:archwood_chest":1,"byg:wilted_grass":2,"byg:cattail":4,"minecraft:crafting_table":2,"minecraft:torch":9,"minecraft:grass_block":7,"betterdefaultbiomes:short_grass":1,"minecraft:spruce_leaves":11,"betterdefaultbiomes:blue_poppy":1,"randomite:randomite_ore":1,"minecraft:seagrass":3,"betterdefaultbiomes:small_rock_mossy":2,"minecraft:tall_seagrass":1,"betterdefaultbiomes:small_rock_stone":7,"ars_nouveau:blue_archwood_log":6,"minecraft:furnace":1,"ars_nouveau:archwood_planks":4,"minecraft:iron_ore":22,"minecraft:spruce_log":13,"projectvibrantjourneys:bark_mushroom":1,"minecraft:coal_ore":95,"projectvibrantjourneys:short_grass":3,"greekfantasy:reeds":3,"minecraft:dirt":18,"ars_nouveau:arcane_ore":4,"minecraft:stone":35},"minecraft:dropped":{"minecraft:bowl":1,"greekfantasy:reeds":6,"betterdefaultbiomes:small_rock_stone":1,"byg:cattail":6,"minecraft:ink_sac":2,"betterdefaultbiomes:tall_water_reeds":1,"projectvibrantjourneys:cattail":1,"projectvibrantjourneys:bark_mushroom":6},"minecraft:picked_up":{"mushroomquest:beefsteakfungus":1,"minecraft:crafting_table":2,"minecraft:iron_chestplate":1,"minecraft:clay_ball":1,"mysticalworld:lustrous_pearl":1,"minecraft:oak_log":1,"minecraft:lapis_lazuli":9,"minecraft:dirt":25,"ars_nouveau:archwood_planks":4,"betterdefaultbiomes:gray_mushroom":3,"greekfantasy:reeds":6,"mysticalworld:raw_squid":1,"ars_nouveau:mana_gem":4,"minecraft:apple":1,"minecraft:iron_ore":22,"betterdefaultbiomes:tall_water_reeds":1,"spartanshields:shield_basic_wood":1,"betterdefaultbiomes:small_rock_mossy":2,"minecraft:furnace":1,"minecraft:book":1,"minecraft:stick":3,"projectvibrantjourneys:bark_mushroom":6,"minecraft:torch":25,"ars_nouveau:blue_archwood_log":6,"ars_nouveau:archwood_chest":3,"betterdefaultbiomes:small_rock_stone":10,"minecraft:spruce_sapling":9,"minecraft:ink_sac":2,"minecraft:spruce_log":13,"byg:cattail":6,"mushroomquest:goldenoyster":1,"simplefarming:raw_calamari":1,"betterdefaultbiomes:blue_poppy":1,"minecraft:iron_helmet":1,"fins:swamp_mucker":3,"minecraft:gold_ingot":1,"projectvibrantjourneys:cattail":3,"minecraft:coal":95,"minecraft:cobblestone":35},"minecraft:crafted":{"minecraft:oak_planks":4,"mysticalworld:cooked_squid":1,"minecraft:crafting_table":1,"ars_nouveau:archwood_planks":24,"minecraft:spruce_planks":52,"minecraft:wooden_pickaxe":1,"minecraft:baked_potato":6,"minecraft:iron_helmet":1,"minecraft:furnace":1,"simplefarming:fried_calamari":1,"minecraft:iron_chestplate":1,"minecraft:cobblestone":2,"minecraft:stick":8,"minecraft:iron_ingot":21,"minecraft:stone_pickaxe":1,"minecraft:wooden_axe":1,"minecraft:chest":1,"minecraft:torch":8},"minecraft:used":{"randomite:randomite_ore":1,"minecraft:iron_ore":1,"minecraft:stone_pickaxe":112,"minecraft:chest":1,"minecraft:wooden_pickaxe":48,"minecraft:torch":7,"minecraft:dirt":25,"betterdefaultbiomes:small_rock_mossy":2,"minecraft:crafting_table":2,"ars_nouveau:archwood_planks":4,"ars_nouveau:archwood_chest":1,"minecraft:wooden_axe":30,"minecraft:apple":1,"betterdefaultbiomes:gray_mushroom":3,"betterdefaultbiomes:small_rock_stone":1,"simplefarming:fried_calamari":1,"betterdefaultbiomes:blue_poppy":1,"minecraft:cobblestone":17,"mushroomquest:goldenoyster":1,"minecraft:furnace":2,"mysticalworld:cactus_sword":28,"projectvibrantjourneys:cattail":2,"mushroomquest:beefsteakfungus":1,"mysticalworld:cooked_squid":1}},"DataVersion":2586}